[
  {
    "date": "2026-04-20T17:39:20.967246+00:00",
    "districts": {
      "vake_saburtalo": {
        "sample_size": 238,
        "median": 1585.0,
        "median_new_build": 1424.0,
        "median_resale": 1635.0
      },
      "isani_samgori": {
        "sample_size": 237,
        "median": 1425.0,
        "median_new_build": 1535.0,
        "median_resale": 1389.0
      },
      "gldani_nadzaladevi": {
        "sample_size": 240,
        "median": 1414.0,
        "median_new_build": 1577.0,
        "median_resale": 1299.0
      },
      "didube_chugureti": {
        "sample_size": 240,
        "median": 1647.0,
        "median_new_build": 1481.0,
        "median_resale": 1675.0
      },
      "dzveli_tbilisi": {
        "sample_size": 239,
        "median": 2200.5,
        "median_new_build": null,
        "median_resale": 2143.0
      }
    }
  },
  {
    "date": "2026-04-21T15:52:04.940057+00:00",
    "districts": {
      "vake_saburtalo": {
        "sample_size": 238,
        "median": 1569.5,
        "median_new_build": 1424.0,
        "median_resale": 1612.0
      },
      "isani_samgori": {
        "sample_size": 239,
        "median": 1450.0,
        "median_new_build": 1524.0,
        "median_resale": 1443.0
      },
      "gldani_nadzaladevi": {
        "sample_size": 239,
        "median": 1378.5,
        "median_new_build": 1492.0,
        "median_resale": 1318.0
      },
      "didube_chugureti": {
        "sample_size": 240,
        "median": 1622.0,
        "median_new_build": 1808.0,
        "median_resale": 1587.0
      },
      "dzveli_tbilisi": {
        "sample_size": 238,
        "median": 2200.0,
        "median_new_build": null,
        "median_resale": 2168.0
      }
    }
  },
  {
    "date": "2026-04-21T19:16:58.488345+00:00",
    "subdistricts": {
      "ლისის ტბა": {
        "sample_size": 22,
        "median": 1793.5,
        "median_new_build": 1665.0,
        "median_resale": 1891.5
      },
      "ვაკე": {
        "sample_size": 24,
        "median": 2628.0,
        "median_new_build": null,
        "median_resale": 2672.0
      },
      "საბურთალო": {
        "sample_size": 128,
        "median": 1768.5,
        "median_new_build": 1915.0,
        "median_resale": 1747.5
      },
      "ბაგები": {
        "sample_size": 12,
        "median": 2004.5,
        "median_new_build": null,
        "median_resale": 2097.0
      },
      "ლილო": {
        "sample_size": 5,
        "median": 1015.0,
        "median_new_build": null,
        "median_resale": 1015.0
      },
      "დიდუბე": {
        "sample_size": 132,
        "median": 1702.5,
        "median_new_build": 2009.0,
        "median_resale": 1657.0
      },
      "ვერა": {
        "sample_size": 104,
        "median": 2432.0,
        "median_new_build": 2990.0,
        "median_resale": 2367.0
      },
      "ელია": {
        "sample_size": 12,
        "median": 1167.0,
        "median_new_build": null,
        "median_resale": 1167.0
      },
      "მთაწმინდა": {
        "sample_size": 101,
        "median": 2388.0,
        "median_new_build": null,
        "median_resale": 2318.0
      }
    }
  },
  {
    "date": "2026-04-27T12:07:43.125586+00:00",
    "subdistricts": {
      "საბურთალო": {
        "sample_size": 114,
        "median": 1921.0,
        "median_new_build": 1906.0,
        "median_resale": 1950.0
      },
      "ვაკე": {
        "sample_size": 33,
        "median": 2362.0,
        "median_new_build": 2500.0,
        "median_resale": 2305.0
      },
      "ლისის ტბა": {
        "sample_size": 21,
        "median": 1844.0,
        "median_new_build": null,
        "median_resale": 1773.5
      },
      "ბაგები": {
        "sample_size": 5,
        "median": 2459.0,
        "median_new_build": null,
        "median_resale": 2459.0
      },
      "ზაჰესი": {
        "sample_size": 5,
        "median": 954.0,
        "median_new_build": null,
        "median_resale": null
      },
      "დიდუბე": {
        "sample_size": 145,
        "median": 1646.0,
        "median_new_build": 1582.5,
        "median_resale": 1657.0
      },
      "ვერა": {
        "sample_size": 96,
        "median": 2302.0,
        "median_new_build": 2524.0,
        "median_resale": 2200.0
      },
      "მთაწმინდა": {
        "sample_size": 97,
        "median": 2245.0,
        "median_new_build": null,
        "median_resale": 2234.5
      },
      "ელია": {
        "sample_size": 12,
        "median": 1523.0,
        "median_new_build": null,
        "median_resale": 1523.0
      }
    }
  }
]